daipecore/DaipeCore.py
daipecore/DaipeCoreTest.py
daipecore/_config/config.yaml
daipecore/_config/config_test.yaml
daipecore/bootstrap/config.py
daipecore/bootstrap/config_reader.py
daipecore/bootstrap/container_factory.py
daipecore/container/ConfigsWatcherThread.py
daipecore/container/WatcherLogger.py
daipecore/container/container_refresher.py
daipecore/decorator/BaseDecorator.py
daipecore/decorator/ContainerManager.py
daipecore/decorator/ContainerManagerTest.py
daipecore/decorator/DecoratedDecorator.py
daipecore/decorator/DecoratedFunctionInjector.py
daipecore/decorator/InputDecorator.py
daipecore/decorator/OutputDecorator.py
daipecore/decorator/StringableParameterInterface.py
daipecore/decorator/notebook_function.py
daipecore/decorator/tests/notebook_function2_test.py
daipecore/decorator/tests/notebook_function_fixture.py
daipecore/decorator/tests/notebook_function_test.py
daipecore/decorator/utils.py
daipecore/detector.py
daipecore/function/ArgumentResolver.py
daipecore/function/ArgumentResolverTest.py
daipecore/function/ArgumentsResolver.py
daipecore/function/arguments_transformer.py
daipecore/function/arguments_transformer_test.py
daipecore/function/function_inspector.py
daipecore/function/input_decorator_function.py
daipecore/function/input_decorator_function_basic_test/decorator_functions.py
daipecore/function/input_decorator_function_basic_test/input_decorator_function_basic_test.py
daipecore/function/input_decorator_function_import_test/decorator_functions.py
daipecore/function/input_decorator_function_import_test/input_decorator_function_import_test.py
daipecore/function/input_decorator_function_import_test/test_notebook.py
daipecore/function/input_decorator_function_nested_test/decorator_functions.py
daipecore/function/input_decorator_function_nested_test/input_decorator_function_nested_test.py
daipecore/imports.py
daipecore/lineage/DecoratorParserInterface.py
daipecore/lineage/GenericOutputDecorator.py
daipecore/lineage/GenericOutputDecoratorParser.py
daipe_core-1.4.4.dist-info/entry_points.txt
daipe_core-1.4.4.dist-info/LICENSE
daipe_core-1.4.4.dist-info/WHEEL
daipe_core-1.4.4.dist-info/METADATA
daipe_core-1.4.4.dist-info/RECORD
