Metadata-Version: 2.1
Name: daipe-core
Version: 1.4.4
Summary: Daipe framework core
Home-page: https://github.com/daipe-ai/daipe-core
License: MIT
Author: Jiri Koutny
Author-email: jiri.koutny@datasentics.com
Requires-Python: >=3.8,<4.0
Classifier: License :: OSI Approved :: MIT License
Classifier: Operating System :: OS Independent
Classifier: Programming Language :: Python :: 3
Classifier: Programming Language :: Python :: 3.8
Classifier: Programming Language :: Python :: 3.9
Requires-Dist: console-bundle (>=0.5,<0.6)
Requires-Dist: injecta (>=0.10.0,<0.11.0)
Requires-Dist: logger-bundle (>=0.7.0,<0.8.0)
Requires-Dist: pandas (>=1.0.1,<2.0.0)
Requires-Dist: pyfony-bundles (>=0.4.0,<0.5.0)
Project-URL: Repository, https://github.com/daipe-ai/daipe-core
